{
  "tables": [
    {
      "id": "tenant",
      "name": "tenant",
      "comment": "Este é o licenciado que está contratando o sistema.",
      "x": -566.7990790845206,
      "y": -203.09160112294114,
      "locked": false,
      "fields": [
        {
          "id": "id",
          "name": "id",
          "comment": "Identificador do licenciado.",
          "type": "BIGINT",
          "default": "",
          "check": "",
          "primary": true,
          "unique": true,
          "notNull": true,
          "increment": true
        },
        {
          "id": "name",
          "name": "name",
          "comment": "Nome completo do licenciado.",
          "type": "TEXT",
          "default": "",
          "check": "",
          "primary": false,
          "unique": false,
          "notNull": true,
          "increment": false,
          "size": "",
          "values": []
        },
        {
          "id": "display_name",
          "name": "display_name",
          "comment": "Nome do licenciado.",
          "type": "TEXT",
          "default": "",
          "check": "",
          "primary": false,
          "unique": false,
          "notNull": true,
          "increment": false,
          "size": "",
          "values": []
        }
      ],
      "indices": [],
      "color": "#FFFF00"
    },
    {
      "id": "account",
      "name": "account",
      "comment": "Esta é a conta do usuário do sistema.",
      "x": 392.2134428868419,
      "y": -167.9444226708904,
      "locked": false,
      "fields": [
        {
          "id": "id",
          "name": "id",
          "comment": "Identificador da conta do usuário.",
          "type": "BIGINT",
          "default": "",
          "check": "",
          "primary": true,
          "unique": true,
          "notNull": true,
          "increment": true
        },
        {
          "id": "name",
          "name": "name",
          "comment": "Nome completo da conta do usuário.",
          "type": "TEXT",
          "default": "",
          "check": "",
          "primary": false,
          "unique": false,
          "notNull": true,
          "increment": false,
          "size": "",
          "values": []
        },
        {
          "id": "display_name",
          "name": "display_name",
          "comment": "Nome do usuário da conta.",
          "type": "TEXT",
          "default": "",
          "check": "",
          "primary": false,
          "unique": false,
          "notNull": true,
          "increment": false,
          "size": "",
          "values": []
        },
        {
          "id": "email",
          "name": "email",
          "comment": "Email da conta do usuário, ligado ao provedor de autenticação.",
          "type": "TEXT",
          "default": "",
          "check": "",
          "primary": false,
          "unique": false,
          "notNull": true,
          "increment": false,
          "size": "",
          "values": []
        },
        {
          "id": "provider",
          "name": "provider",
          "comment": "Indica qual foi o mecanismo de autenticação utilizado pela conta do usuário (ex.: google auth).",
          "type": "TEXT",
          "default": "",
          "check": "",
          "primary": false,
          "unique": false,
          "notNull": true,
          "increment": false,
          "size": "",
          "values": []
        },
        {
          "id": "provider_subject",
          "name": "provider_subject",
          "comment": "Identificador estável da conta no provedor de autenticação.",
          "type": "TEXT",
          "default": "",
          "check": "",
          "primary": false,
          "unique": false,
          "notNull": true,
          "increment": false,
          "size": "",
          "values": []
        }
      ],
      "constraints": [
        {
          "name": "account_unique_email",
          "constraint": "UNIQUE (email)"
        },
        {
          "name": "account_unique_provider_subject",
          "constraint": "UNIQUE (provider, provider_subject)"
        }
      ],
      "indices": [],
      "color": "#FFFF00"
    },
    {
      "id": "member",
      "name": "member",
      "comment": "Esté o usuário do sistema em um determinado licenciado.",
      "x": -81.47387490923484,
      "y": -364.4327648486604,
      "locked": false,
      "fields": [
        {
          "id": "id",
          "name": "id",
          "comment": "Identificador do usuário.",
          "type": "BIGINT",
          "default": "",
          "check": "",
          "primary": true,
          "unique": true,
          "notNull": true,
          "increment": true
        },
        {
          "id": "name",
          "name": "name",
          "comment": "Nome completo do usuário.",
          "type": "TEXT",
          "default": "",
          "check": "",
          "primary": false,
          "unique": false,
          "notNull": false,
          "nullIfEmpty": true,
          "increment": false,
          "size": "",
          "values": []
        },
        {
          "id": "display_name",
          "name": "display_name",
          "comment": "Nome do usuário.",
          "type": "TEXT",
          "default": "",
          "check": "",
          "primary": false,
          "unique": false,
          "notNull": false,
          "nullIfEmpty": true,
          "increment": false,
          "size": "",
          "values": []
        },
        {
          "id": "email",
          "name": "email",
          "comment": "Email do usuário.",
          "type": "TEXT",
          "default": "",
          "check": "",
          "primary": false,
          "unique": false,
          "notNull": true,
          "increment": false,
          "size": "",
          "values": []
        },
        {
          "id": "tenant_id",
          "name": "tenant_id",
          "comment": "Ligação do usuário ao licenciado.",
          "type": "BIGINT",
          "default": "",
          "check": "",
          "primary": false,
          "unique": false,
          "notNull": true,
          "increment": false,
          "size": "",
          "values": []
        },
        {
          "id": "account_id",
          "name": "account_id",
          "comment": "Ligação do usuário à conta do usuário.",
          "type": "BIGINT",
          "default": "",
          "check": "",
          "primary": false,
          "unique": false,
          "notNull": false,
          "increment": false,
          "size": "",
          "values": []
        },
        {
          "id": "role",
          "name": "role",
          "comment": "Papel do usuário no licenciado: 1 master, 2 admin, 3 member.",
          "type": "INTEGER",
          "default": "3",
          "check": "role IN (1, 2, 3)",
          "primary": false,
          "unique": false,
          "notNull": true,
          "increment": false,
          "size": "",
          "values": []
        },
        {
          "id": "status",
          "name": "status",
          "comment": "Situação do usuário: 1 ativo, 2 pendente, 3 desativado.",
          "type": "INTEGER",
          "default": "",
          "check": "status IN (1, 2, 3)",
          "primary": false,
          "unique": false,
          "notNull": true,
          "increment": false,
          "size": "",
          "values": []
        },
        {
          "id": "current_scope_id",
          "name": "current_scope_id",
          "comment": "Escopo atualmente selecionado pelo usuário dentro do licenciado.",
          "type": "BIGINT",
          "default": "",
          "check": "",
          "primary": false,
          "unique": false,
          "notNull": false,
          "increment": false,
          "size": "",
          "values": []
        }
      ],
      "constraints": [
        {
          "name": "member_name_empty",
          "constraint": "status = 2 OR name IS NOT NULL"
        },
        {
          "name": "member_display_name_empty",
          "constraint": "status = 2 OR display_name IS NOT NULL"
        },
        {
          "name": "member_unique_tenant_account",
          "constraint": "UNIQUE (tenant_id, account_id) WHERE account_id IS NOT NULL"
        }
      ],
      "indices": [],
      "color": "#FFFF00"
    },
    {
      "id": "scope",
      "name": "scope",
      "comment": "Escopo do projeto: Aves, Soja, Leite...",
      "indices": [],
      "color": "#ff0000",
      "fields": [
        {
          "id": "id",
          "name": "id",
          "comment": "Identificador do escopo.",
          "type": "BIGINT",
          "default": "",
          "check": "",
          "primary": true,
          "unique": true,
          "notNull": true,
          "increment": true,
          "size": "",
          "values": []
        },
        {
          "id": "name",
          "name": "name",
          "comment": "Nome do escopo: Aves, Soja, Leite...",
          "type": "TEXT",
          "default": "",
          "check": "",
          "primary": false,
          "unique": false,
          "notNull": true,
          "increment": false,
          "size": "",
          "values": []
        },
        {
          "id": "display_name",
          "name": "display_name",
          "comment": "Descrição do escopo: Aves para produção de ovos, Soja em grãos, Leite...",
          "type": "TEXT",
          "default": "",
          "check": "",
          "primary": false,
          "unique": false,
          "notNull": true,
          "increment": false,
          "size": "",
          "values": []
        },
        {
          "id": "tenant_id",
          "name": "tenant_id",
          "comment": "Ligação do escopo ao licenciado.",
          "type": "BIGINT",
          "default": "",
          "check": "",
          "primary": false,
          "unique": false,
          "notNull": true,
          "increment": false,
          "size": "",
          "values": []
        }
      ],
      "x": -680.9582181240327,
      "y": 290.60076147272224
    },
    {
      "id": "location",
      "name": "location",
      "comment": "Local onde ocorre a operação: Granja, Unidade, Aviário, Subdivisão...",
      "indices": [],
      "color": "#ff0000",
      "fields": [
        {
          "id": "id",
          "name": "id",
          "comment": "Identificador do local.",
          "type": "BIGINT",
          "default": "",
          "check": "",
          "primary": true,
          "unique": true,
          "notNull": true,
          "increment": true,
          "size": "",
          "values": []
        },
        {
          "id": "name",
          "name": "name",
          "comment": "Nome do local: Granja A, Unidade Sul, Aviário B, Subdivisão Tal...",
          "type": "TEXT",
          "default": "",
          "check": "",
          "primary": false,
          "unique": false,
          "notNull": true,
          "increment": false,
          "size": "",
          "values": []
        },
        {
          "id": "display_name",
          "name": "display_name",
          "comment": "Descrição do local: Granja A para produção de ovos, Unidade Sul para produção de leite, Aviário B para produção de aves, Subdivisão Tal para produção de soja...",
          "type": "TEXT",
          "default": "",
          "check": "",
          "primary": false,
          "unique": false,
          "notNull": true,
          "increment": false,
          "size": "",
          "values": []
        },
        {
          "id": "parent_location_id",
          "name": "parent_location_id",
          "comment": "Ligação do local ao local pai, por exemplo, Unidade Sul fica dentro da Granja A.",
          "type": "BIGINT",
          "default": "",
          "check": "",
          "primary": false,
          "unique": false,
          "notNull": false,
          "increment": false,
          "size": "",
          "values": []
        },
        {
          "id": "scope_id",
          "name": "scope_id",
          "comment": "Ligação do local ao escopo.",
          "type": "BIGINT",
          "default": "",
          "check": "",
          "primary": false,
          "unique": false,
          "notNull": true,
          "increment": false,
          "size": "",
          "values": []
        },
        {
          "id": "sort_order",
          "name": "sort_order",
          "comment": "Ordem de exibição do local na hierarquia.",
          "type": "INTEGER",
          "default": "0",
          "check": "",
          "primary": false,
          "unique": false,
          "notNull": true,
          "increment": false,
          "size": "",
          "values": []
        }
      ],
      "x": -83.23652412756303,
      "y": 131.98117626059718
    },
    {
      "id": "unity",
      "name": "unity",
      "comment": "Use para cadastrar a unidade produtiva. Pode ser, por exemplo: galinha, fêmea, branca, vermelha.",
      "color": "#ff0000",
      "indices": [],
      "fields": [
        {
          "id": "id",
          "name": "id",
          "comment": "Identificação da unidade produtiva.",
          "type": "BIGINT",
          "default": "",
          "check": "",
          "primary": true,
          "unique": true,
          "notNull": true,
          "increment": true,
          "size": "",
          "values": []
        },
        {
          "id": "name",
          "name": "name",
          "comment": "Nome curto da unidade produtiva.",
          "type": "TEXT",
          "default": "",
          "check": "",
          "primary": false,
          "unique": false,
          "notNull": true,
          "increment": false,
          "size": "",
          "values": []
        },
        {
          "id": "display_name",
          "name": "display_name",
          "comment": "Descrição da unidade produtiva.",
          "type": "TEXT",
          "default": "",
          "check": "",
          "primary": false,
          "unique": false,
          "notNull": true,
          "increment": false,
          "size": "",
          "values": []
        },
        {
          "id": "parent_unity_id",
          "name": "parent_unity_id",
          "comment": "Em caso de hierarquia, esta á a unidade produtiva a qual esta pertence.",
          "type": "BIGINT",
          "default": "",
          "check": "",
          "primary": false,
          "unique": false,
          "notNull": false,
          "increment": false,
          "size": "",
          "values": []
        },
        {
          "id": "scope_id",
          "name": "scope_id",
          "comment": "Escopo desta unidade produtiva.",
          "type": "BIGINT",
          "default": "",
          "check": "",
          "primary": false,
          "unique": false,
          "notNull": true,
          "increment": false,
          "size": "",
          "values": []
        },
        {
          "id": "sort_order",
          "name": "sort_order",
          "comment": "Ordem da unidade produtiva em relação às demais de mesmo nível.",
          "type": "INTEGER",
          "default": "0",
          "check": "",
          "primary": false,
          "unique": false,
          "notNull": true,
          "increment": false,
          "size": "",
          "values": []
        }
      ],
      "x": -85.23192874460136,
      "y": 510.82134408336117
    },
    {
      "id": "log",
      "name": "log",
      "comment": "Esta tabela registra todas as modificações feitas nas demais tabelas.",
      "color": "#00aa00",
      "indices": [],
      "fields": [
        {
          "id": "id",
          "name": "id",
          "comment": "Identificador do log",
          "type": "BIGINT",
          "default": "",
          "check": "",
          "primary": true,
          "unique": true,
          "notNull": true,
          "increment": true,
          "size": "",
          "values": []
        },
        {
          "id": "account_id",
          "name": "account_id",
          "comment": "Ligação com a conta do usuário que fez a modificação",
          "type": "BIGINT",
          "default": "",
          "check": "",
          "primary": false,
          "unique": false,
          "notNull": true,
          "increment": false,
          "size": "",
          "values": []
        },
        {
          "id": "tenant_id",
          "name": "tenant_id",
          "comment": "Ligação com o licenciado que fez a ligação.",
          "type": "BIGINT",
          "default": "",
          "check": "",
          "primary": false,
          "unique": false,
          "notNull": true,
          "increment": false,
          "size": "",
          "values": []
        },
        {
          "id": "table_name",
          "name": "table_name",
          "comment": "Nome da tabela que foi modificada",
          "type": "TEXT",
          "default": "",
          "check": "table_name IN ( 'tenant', 'account', 'member', 'scope', 'location', 'unity' )",
          "primary": false,
          "unique": false,
          "notNull": true,
          "increment": false,
          "size": "",
          "values": []
        },
        {
          "id": "action_type",
          "name": "action_type",
          "comment": "Tipo da modificação feita: insert, update ou delete.",
          "type": "TEXT",
          "default": "",
          "check": "action_type IN ( 'I', 'U', 'D' )",
          "primary": false,
          "unique": false,
          "notNull": true,
          "increment": false,
          "size": "",
          "values": []
        },
        {
          "id": "row",
          "name": "row",
          "comment": "Conteúdo da linha. JSONB vazio em caso de delete.",
          "type": "JSONB",
          "default": "",
          "check": "",
          "primary": false,
          "unique": false,
          "notNull": true,
          "increment": false,
          "size": "",
          "values": []
        },
        {
          "id": "moment_utc",
          "name": "moment_utc",
          "comment": "Momento em que ocorreu a ação.",
          "type": "TIMESTAMP",
          "default": "now() at time zone 'UTC'",
          "check": "",
          "primary": false,
          "unique": false,
          "notNull": true,
          "increment": false,
          "size": "",
          "values": []
        }
      ],
      "x": -560.1361397830926,
      "y": -665.0369646216051
    }
  ],
  "relationships": [
    {
      "id": "member.tenant_id",
      "name": "member.tenant_id",
      "startTableId": "tenant",
      "startFieldId": "id",
      "endTableId": "member",
      "endFieldId": "tenant_id",
      "cardinality": "one_to_many",
      "updateConstraint": "Cascade",
      "deleteConstraint": "Restrict"
    },
    {
      "id": "member.account_id",
      "name": "member.account_id",
      "startTableId": "account",
      "startFieldId": "id",
      "endTableId": "member",
      "endFieldId": "account_id",
      "cardinality": "one_to_many",
      "updateConstraint": "Cascade",
      "deleteConstraint": "Set null"
    },
    {
      "id": "scope.tenant_id",
      "name": "scope.tenant_id",
      "startTableId": "tenant",
      "startFieldId": "id",
      "endTableId": "scope",
      "endFieldId": "tenant_id",
      "cardinality": "one_to_many",
      "updateConstraint": "Cascade",
      "deleteConstraint": "Restrict"
    },
    {
      "id": "location.scope_id",
      "name": "location.scope_id",
      "startTableId": "scope",
      "startFieldId": "id",
      "endTableId": "location",
      "endFieldId": "scope_id",
      "cardinality": "one_to_many",
      "updateConstraint": "Cascade",
      "deleteConstraint": "Restrict"
    },
    {
      "id": "location.parent_location_id",
      "name": "location.parent_location_id",
      "startTableId": "location",
      "startFieldId": "id",
      "endTableId": "location",
      "endFieldId": "parent_location_id",
      "cardinality": "one_to_many",
      "updateConstraint": "Cascade",
      "deleteConstraint": "Cascade"
    },
    {
      "id": "member.current_scope_id",
      "name": "member.current_scope_id",
      "startTableId": "scope",
      "startFieldId": "id",
      "endTableId": "member",
      "endFieldId": "current_scope_id",
      "cardinality": "one_to_many",
      "updateConstraint": "Cascade",
      "deleteConstraint": "Set null"
    },
    {
      "id": "unity.scope_id",
      "name": "unity.scope_id",
      "startTableId": "scope",
      "startFieldId": "id",
      "endTableId": "unity",
      "endFieldId": "scope_id",
      "cardinality": "one_to_many",
      "updateConstraint": "Cascade",
      "deleteConstraint": "Restrict"
    },
    {
      "id": "unity.parent_unity_id",
      "name": "unity.parent_unity_id",
      "startTableId": "unity",
      "startFieldId": "id",
      "endTableId": "unity",
      "endFieldId": "parent_unity_id",
      "cardinality": "one_to_many",
      "updateConstraint": "Cascade",
      "deleteConstraint": "Cascade"
    },
    {
      "id": "log.tenant_id",
      "name": "log.tenant_id",
      "startTableId": "tenant",
      "startFieldId": "id",
      "endTableId": "log",
      "endFieldId": "tenant_id",
      "cardinality": "one_to_many",
      "updateConstraint": "Cascade",
      "deleteConstraint": "Cascade"
    },
    {
      "id": "log.account_id",
      "name": "log.account_id",
      "startTableId": "account",
      "startFieldId": "id",
      "endTableId": "log",
      "endFieldId": "account_id",
      "cardinality": "one_to_many",
      "updateConstraint": "Cascade",
      "deleteConstraint": "Cascade"
    }
  ],
  "notes": [],
  "subjectAreas": [],
  "database": "postgresql",
  "types": [],
  "enums": [],
  "title": "Valora ERD"
}